struct_agent/README.md
struct_agent/__init__.py
struct_agent/instructor_based/__init__.py
struct_agent/instructor_based/client_manager.py
struct_agent/instructor_based/new_agent.py
struct_agent/instructor_based/prompt_manager.py
struct_agent/instructor_based/reasoning_modules.py
struct_agent/instructor_based/tool_manager.py
struct_agent/instructor_based/utils.py
struct_agent/tools/__init__.py
struct_agent/tools/blank_tool.py
struct_agent/tools/leann_tools.py
struct_agent/tools/maths_tools.py
struct_agent/tools/searxng_tools.py
struct_agent/tools/toolkits.py
struct_agent-1.0.2.dist-info/METADATA
struct_agent-1.0.2.dist-info/WHEEL
struct_agent-1.0.2.dist-info/licenses/LICENSE
struct_agent-1.0.2.dist-info/RECORD
