Metadata-Version: 2.4
Name: struct_agent
Version: 1.0.2
Summary: A small, simple, and structured AI agent.
License-Expression: MIT
License-File: LICENSE
Keywords: ai,agent,structured,llm
Author: plomitt
Author-email: 46419727+plomitt@users.noreply.github.com
Requires-Python: >=3.12,<4
Classifier: Development Status :: 4 - Beta
Classifier: Intended Audience :: Developers
Classifier: License :: OSI Approved :: MIT License
Classifier: Operating System :: OS Independent
Classifier: Programming Language :: Python :: 3
Classifier: Programming Language :: Python :: 3.12
Classifier: Topic :: Software Development :: Libraries :: Python Modules
Classifier: Topic :: Scientific/Engineering :: Artificial Intelligence
Requires-Dist: instructor (>=1.3)
Requires-Dist: leann (>=0.3.4,<0.4.0)
Requires-Dist: openai (>=1.30)
Requires-Dist: pydantic (>=2.7)
Project-URL: Documentation, https://github.com/plomitt/struct_agent#readme
Project-URL: Homepage, https://github.com/plomitt/struct_agent
Project-URL: Repository, https://github.com/plomitt/struct_agent
